sicritfix/_init_.py
sicritfix/cli.py
sicritfix/io/io.py
sicritfix/processing/_init_.py
sicritfix/processing/corrector.py
sicritfix/processing/processor.py
sicritfix/utils/frequency_analyzer.py
sicritfix/utils/intensity_analyzer.py
sicritfix/validation/try_file.py
sicritfix/validation/validator.py
sicritfix-0.0.3.dist-info/LICENSE
sicritfix-0.0.3.dist-info/METADATA
sicritfix-0.0.3.dist-info/WHEEL
sicritfix-0.0.3.dist-info/entry_points.txt
sicritfix-0.0.3.dist-info/RECORD
