Metadata-Version: 2.3
Name: sicritfix
Version: 0.0.3
Summary: Python package to detect and correct oscillatory artifacts in mass spectrometry mzML data.
License: GPL-3.0-only
Keywords: mass spectrometry,mzML,signal correction,fft,phase,oscillations
Author: Maite Gómez del Rio Vinuesa
Author-email: maite.gomezriovinuesa@gmail.com
Maintainer: Maite Gómez del Rio Vinuesa
Maintainer-email: maite.gomezriovinuesa@gmail.com
Requires-Python: >=3.11
Classifier: Development Status :: 3 - Alpha
Classifier: Intended Audience :: Science/Research
Classifier: License :: OSI Approved :: GNU General Public License v3 (GPLv3)
Classifier: Operating System :: OS Independent
Classifier: Programming Language :: Python :: 3
Classifier: Programming Language :: Python :: 3.11
Classifier: Programming Language :: Python :: 3.12
Classifier: Programming Language :: Python :: 3.13
Classifier: Programming Language :: Python :: 3.10
Classifier: Programming Language :: Python :: 3.8
Classifier: Programming Language :: Python :: 3.9
Requires-Dist: numpy (>=1.22,<2.0)
Requires-Dist: pyopenms
Requires-Dist: scipy (>=1.8,<2.0)
Project-URL: Documentation, https://github.com/MaiteGomezRio/Oscillations_Corrector_Algorithm_SICRIT#readme
Project-URL: Homepage, https://github.com/MaiteGomezRio/Oscillations_Corrector_Algorithm_SICRIT
Project-URL: Repository, https://github.com/MaiteGomezRio/Oscillations_Corrector_Algorithm_SICRIT
